{
	"parent": "minecraft:block/block",
	"texture_size": [32, 32],
	"textures": {
		"0": "#computer",
		"particle": "#computer"
	},
	"elements": [
		{
			"from": [8, 0, 3],
			"to": [16, 1, 4],
			"rotation": {"angle": -22.5, "axis": "y", "origin": [8, 0, 3]},
			"faces": {
				"north": {"uv": [12, 6, 16, 6.5], "texture": "#0"},
				"east": {"uv": [12, 5.5, 12.5, 6], "texture": "#0"},
				"south": {"uv": [12, 5, 16, 5.5], "texture": "#0"},
				"up": {"uv": [12, 5.5, 16, 6], "texture": "#0"},
				"down": {"uv": [12, 6.5, 16, 7], "texture": "#0"}
			}
		},
		{
			"from": [0, 0, 3],
			"to": [8, 1, 4],
			"rotation": {"angle": 22.5, "axis": "y", "origin": [8, 0, 3]},
			"faces": {
				"north": {"uv": [12, 5, 16, 5.5], "texture": "#0"},
				"south": {"uv": [12, 6, 16, 6.5], "texture": "#0"},
				"west": {"uv": [12, 5.5, 12.5, 6], "texture": "#0"},
				"up": {"uv": [12, 6.5, 16, 7], "rotation": 180, "texture": "#0"},
				"down": {"uv": [12, 5.5, 16, 6], "rotation": 180, "texture": "#0"}
			}
		},
		{
			"from": [7, 0, 3],
			"to": [9, 6, 4],
			"faces": {
				"north": {"uv": [1, 5, 2, 8], "texture": "#0"},
				"east": {"uv": [0, 5, 0.5, 8], "texture": "#0"},
				"south": {"uv": [0, 5, 1, 8], "texture": "#0"},
				"west": {"uv": [0.5, 5, 1, 8], "texture": "#0"},
				"up": {"uv": [1, 7.5, 2, 8], "texture": "#0"},
				"down": {"uv": [1, 5, 2, 5.5], "texture": "#0"}
			}
		},
		{
			"from": [0, 4, 4],
			"to": [16, 14, 5],
			"faces": {
				"north": {"uv": [8, 0, 16, 5], "texture": "#0"},
				"east": {"uv": [15.5, 0, 16, 5], "texture": "#0"},
				"south": {"uv": [0, 0, 8, 5], "texture": "#0"},
				"west": {"uv": [8, 0, 8.5, 5], "texture": "#0"},
				"up": {"uv": [8, 4.5, 16, 5], "texture": "#0"},
				"down": {"uv": [8, 0, 16, 0.5], "texture": "#0"}
			}
		},
		{
			"from": [4, 6, 3],
			"to": [12, 12, 4],
			"faces": {
				"north": {"uv": [0.5, 12.5, 4.5, 15.5], "texture": "#0"},
				"east": {"uv": [0, 12.5, 0.5, 15.5], "texture": "#0"},
				"west": {"uv": [4.5, 12.5, 5, 15.5], "texture": "#0"},
				"up": {"uv": [0.5, 12, 4.5, 12.5], "texture": "#0"},
				"down": {"uv": [0.5, 15.5, 4.5, 16], "texture": "#0"}
			}
		},
		{
			"from": [13, 0, 10],
			"to": [15, 1, 13],
			"faces": {
				"north": {"uv": [0.5, 9, 1.5, 9.5], "texture": "#0"},
				"east": {"uv": [1.5, 9.5, 2, 11], "rotation": 90, "texture": "#0"},
				"south": {"uv": [0.5, 11, 1.5, 11.5], "texture": "#0"},
				"west": {"uv": [0, 9.5, 0.5, 11], "rotation": 90, "texture": "#0"},
				"up": {"uv": [0.5, 9.5, 1.5, 11], "texture": "#0"},
				"down": {"uv": [2, 9.5, 3, 11], "texture": "#0"}
			}
		},
		{
			"from": [1, 0, 9],
			"to": [12, 1, 14],
			"faces": {
				"north": {"uv": [10.5, 11, 16, 11.5], "texture": "#0"},
				"east": {"uv": [15.5, 11, 16, 13.5], "rotation": 90, "texture": "#0"},
				"south": {"uv": [10.5, 13, 16, 13.5], "texture": "#0"},
				"west": {"uv": [10.5, 11, 11, 13.5], "rotation": 90, "texture": "#0"},
				"up": {"uv": [10.5, 13.5, 16, 16], "texture": "#0"},
				"down": {"uv": [10.5, 11, 16, 13.5], "texture": "#0"}
			}
		}
	],
	"display": {
		"thirdperson_righthand": {
			"translation": [0, 3, 1.75],
			"scale": [0.375, 0.375, 0.375]
		},
		"thirdperson_lefthand": {
			"translation": [0, 3, 1.75],
			"scale": [0.375, 0.375, 0.375]
		},
		"firstperson_righthand": {
			"rotation": [0, -45, 0],
			"scale": [0.4, 0.4, 0.4]
		},
		"firstperson_lefthand": {
			"rotation": [0, -45, 0],
			"scale": [0.4, 0.4, 0.4]
		},
		"gui": {
			"rotation": [30, 45, 0],
			"scale": [0.625, 0.625, 0.625]
		},
		"head": {
			"rotation": [0, 180, 0]
		},
		"fixed": {
			"rotation": [0, 180, 0],
			"translation": [0, 0, -1.5],
			"scale": [0.5, 0.5, 0.5]
		}
	}
}